{
  "title": "14_Feb_2020_-_set09",
  "content": "# 14_Feb_2020_-_set09\n\nContent-Type: text/x-zim-wiki\nWiki-Format: zim 0.6\nCreation-Date: 2024-07-23T22:17:55-07:00\n\n====== REC001.txt ======\nyeah it's okay in the game let's see wait I usually carry just a third system\nyou grab the door and character gets pulled through and I'm gonna speed changes a little\nand then inside the space\nand then I'm gonna go ahead and I'm gonna go ahead and I'm gonna go ahead and I'm gonna go ahead and I'm gonna go ahead and I'm gonna go ahead and I'm gonna go ahead and I'm gonna go ahead and I'm gonna go ahead and I'm gonna go ahead and I'm gonna go ahead and I'm gonna go ahead and I'm gonna go ahead\n\n\n====== REC002.txt ======\nI realized it okay\n\n\n====== REC003.txt ======\nGet some smaller independent shelves\nTake a read the room, take a read the walls, get the cat, there you have to climb\nMake it fun for him\nThat'll also decorate a little bit, you know, shelves\nBooks are those all\nWhat does it have to do with the room?\nYou're right on action, it's okay\nYou know, maybe\nOf it\nIf I can do shelves reinstall a bit\nThat TV\nThat TV might have to go\nIt's a good registration\nOr is it sounds?\n\n\n====== REC004.txt ======\nbuild my room. But I want you right at the bed. Where is it sounds? I've got plenty of\npillows, blankets and mattresses. You know, with cushioners. I'll be fine. I don't need\nabout that much emphasis on sleep. The sleep was not that important to me.\n\n\n====== REC005.txt ======\nIt's important to get hours, but when I'm up, when I get up, you know, I'm just gonna be here.\nI need to be more alert.\nI'm gonna wait for your environment.\n\n\n====== REC006.txt ======\nI don't know how you're doing at all.\n\n\n====== REC007.txt ======\nThe reason does not persist in unreasonable society.\nThe reason does not persist in unreasonable society.\n\n\n====== REC008.txt ======\nThat's all right.\n\n\n====== REC009.txt ======\nYou can copy of them in the rolling system, that's in place, the transfer, the animation\nmovement.\nWe're going to use that in a case of you, your role, but if you love that, you transfer\nthem automatically into more of a flooding position, then you do that.\nWhat is it really?\n\n\n====== REC010.txt ======\nThe waters carry cinnamon or no, the towers themselves produce cinnamon, it's like a skin\ngrowing, or tree bark growing really. So there are larynllaires, they're grown to mountains,\nit's under. Inch of this area, it's accessible, it's on microbiome. The people are mad to take\nthese structures, out of the world around.\n\n\n====== REC011.txt ======\nSo they've built their own structures, they're there in the main service but then below\nthey found, they've discovered that there's the remnants of what could have\nfertilization, these fast underground labyrinths, these are the levels beyond the main\nday, I suppose, with the first system, in place that's perfect, and you traverse with people,\nyou coordinate with people and that's the main mechanic, that's what I want to build\nthere, that's right, we're good to meet them.\n\n\n====== REC012.txt ======\nfuture and light down the game, it sounds funny, but\nso, the only way to make the game is to lay it out\nto sleep somewhere,\ndepressed\nand there are lots of places to rest while they're on the road\nthey're recursive when you say that when you just\npress A in the characters\nthe characters just\nslept in, slept in those rooms\nyou know, why?\nlight down the bed, sitting somewhere\njust sitting on a ledge\njust move out of the heart and then\nwhen they leave\nthe body heartens\nit stays there\nit's like a\ndecoration machine\nit's that friend\nwhen they come back, it'll\ngo back to form\nand they can move again\nand there's a lot of stuff later to come back\nthat frame remains\n\n\n====== REC013.txt ======\nto pull up and pick something up and lay it somewhere else.\nThe other remains and it collects some dust and it's big.\nAnd whether is it a rose?\nWell, no, life is ugly.\nJust imagine a pale kitchen order, right?\nThat's very good example.\n\n\n====== REC014.txt ======\nWell, I'd love to see plant scrum plumber.\nI've got to pick these three days carefully.\n\n\n====== REC015.txt ======\nThere's four spaces, I think, visiting places.\nCan't I do it any time?\n\n\n====== REC016.txt ======\nThe game and their person is how I intended to be for the majority of the story, but there are other stories again.\nI think it'd be a bit more disturbing, but what if it's not?\nNo, it's more a Christian man.\n\n\n====== REC017.txt ======\nSo let's go with the third person traversing system as unit, but I'd like to introduce\na VR mode for the parkies, the hands, and the sunshine, but this character is a representation\nof themselves. We have to just customize that. Everything else is pre-faceted. See the\nplayer was a... just a cephalon really, and they're given a new body after being stasis, being\nin the brain not being destroyed, because it's flushed with the anti-freezing solution and\nit's not water, necessarily, or it's a mixture that prevents. Okay, so if it was just water,\nthen there were cells of freeze and cells of freeze. Well, it breaks because when water freezes,\nit expands and the cells of it destroyed, so you had a anti-freezing solution and the brain\nis preserved.\n\n\n====== REC018.txt ======\nSo, the main player controller is the end of the third person and the first person when\nyou enter a server home.\nHere's the 50 animation that exists.\nAnd you can also press if you need to go first person.\nI need to figure out this, and I'm testing it, but I think that's the way to go.\nI may remove the hands, the floating hands, because they're going to bite less.\nAs long as the player game isn't dead, it's fine.\nI'm OK to use the right animation as this.\nSo, you should find one that's going to stay less in the care of this person.\n\n\n====== REC019.txt ======\nI will leave the arm out to her, there it was, is what I was thinking.\nIn this case they have voice, and the person version they don't have voice from the person\nyou can interact in a different way than the player again.\nI will leave the arm out to her, there it was, there it was, there it was, there it was, there it was, there it was, there it was, there it was, there it was, there it was, there it was, there it was, there it was, there it was, there it was, there it was, there it was, there it was, there it was, there it was, there it was, there it was, there it was, there it was, there it was, there it was, there it was, there it was, there it was, there it was, there it was, there it was, there it was, there it was, there it was, there it was, there it was, there it was, there it was, there it was, there it was, there it was, there it was, there it was, there it was, there it was, there it was, there it was, there it was, there it was, there it was, there it was, there it was, there it\n\n\n====== REC020.txt ======\nOkay, well that's interesting enough so VR mode doesn't have a story necessarily the characters\nYou can still interact with the people using the third person controllers\nBut in VR\nYou have your own body, you just don't know the little mechanics of\nYou can climb still, it just takes a little more effort\nIt gets you to get in\nBut you can get help from this\nDodak, it's funny as that is\nYou can access your towering creatures\nI'm not sure if we have really large depends on how I guess I don't mind.\n\n\n====== REC021.txt ======\nThe third person when traversing the world, the first person when entering home, the VR mode is the first mode, slash first person mode as the Timu character controller.\nA crystalline creature that can express themselves with a clothing and other accessories.\nAnd then there's the VR version, the VR version is more...\nThe VR mode is more yourself as opposed to you're given an avatar using that.\nYou don't got to smile about it just that because that is all there is.\nYou can modify parts that you're dealing with.\nIt's a controller, I should say.\nThe VR mode is the Timu.\nOh boy, let's go and scan our decals.\n\n\n====== REC022.txt ======\nwhich use cylinders and spheres to build the initial terrain without the use of any\nbuilt-in terrain system.\n\n\n====== REC023.txt ======\nAnd then I've had a mesh combination.\nI can just turn those into simple meshes,\nbut I was pretty good.\nWell, I like to like your day of being able to shape the interior\nof the terrain with large objects that get the feel right,\nand then decorate it.\nYou're imagining just adding a ration to my shapes.\n\n\n====== REC024.txt ======\nIf I had an erosion shader for basic shapes, imagine a bill, right, full shape, and you have\nnot a layer top set, the layer top set has a physically based plane that draws objects\nbelow it. The planet's office guarded towards the gravity of the planet, and then you could\nlike that if we have large bills that are physically accurate to a given area. I had a\ntranscendence over the curvature of the planet, over the asteroid that I know that you're\nslowly going to make. That means large shader. I'm going to go over first to have this\nsurface.\n\n\n====== REC025.txt ======\nHe's faking the water necessary. We're going to use the lighting data to better represent the water.\nIt seems the lighting I have right now is ink from congruence with the lighting we see on Earth.\nSo either the planet I have is too large and should be smaller to the size of Europa.\nBy that I mean that you need to get rid of it.\nOr I've got the scaling wrong on the atmosphere.\nBecause right now it just feels a little relative to the potential I've seen it been used.\n\n\n====== REC026.txt ======\nTry to emulate that system again, let's see if it looks green or not, I'm really, experimented.\nDon't be afraid.\n\n\n====== REC027.txt ======\nI have another character, so I have a considered part of it.\nI have considered it in Marianne.\nLet's go on to Wilman French.\n\n\n====== REC028.txt ======\n1,5,5,5,5,5,5,5,5,5,5,5,5,5,5,5,5,5,5,5,5,5,5,5,5,5,5,5,5,5,5,5,5,5,5,5,5,5,5,5,5,5,5,5,5,5,5,5,5,5,5,5,5,5,5,5,5,5,5,5,5,5,5,5,5,5,5,5,5,5,5,5,5,5,5,5,5,5,5,5,5,5,5,5,5,5,5,5,5,5,5,5,5,5,5,5,5,5,5,5,5,5,5,5,5,5,5,5,5,5,5,5\nWell, man, is...\n\n\n====== REC029.txt ======\nSo, well, man, yes, a biologist, he hopes to begin\nan exobiologist, but they've yet to find any sense of life. So, he's found himself in\nexobiology, archaeology, really. Trying to make sense of the world, trying to make sense of these\nstructures. So, he's more an explorer and architect, but he uses training systems to\narchitect the space. You'll have them fight them on the training system, which means\nit's due. You're a sense of this. You're a sense of this.\n\n\n====== REC030.txt ======\nDestructions, destructions feel that the wood is not meaning, and yet confirm not anything\nbecause there's no history without being reasoned, but I can't know for certain about\ncontent, and if we can produce the structures in the tote, and we'll approach together, he\nknows quite a bit what he doesn't, he can't pull a piece together yet, after all life\nDemocerate, he doesn't feel any, anything concrete to move forward with, he's stuck, that is a\nway forward life, if he has no clear image, no clear goal, if the water will reach his\n\n\n====== REC031.txt ======\nI should think a little more elegantly about the solar collectors that rode in around the\nlocal star. I think I have an idea now.\n\n\n====== REC032.txt ======\nSo\nQC Prims has this awesome\nbasic shaped neck\nsystem and I can make a\ncircular structure and clip it at a point\nand I get a\nwell\nshape the cylinders to put the looks best and then have them rotate around\nthe star that we are collecting good material I put all of it\nand I'll have to find a way to\nany motionos with the look structures at some point\nfor now it's\naesthetic pleasing\nif you've got these either\ncylinder or\ntubes or\nMarshall cylinders\nrotating around this one\ncollecting a magic\n\n\n====== REC033.txt ======\nSo, a woman being the practical guy that he is, has grown weary of the present day.\nIt will be, it will be, it will be, it will be, it will be, it will be, it will be,\nSometimes, with no, they're able to reach the center of the atmosphere, or to find any.\nI mean, the flounder is into it.\nHe thinks he believes it to be just a vaneous system.\nHe doesn't know the immense lead.\nBesides, when they start to freeze.\n\n\n====== REC034.txt ======\nThe stars have been going dim for two or three thousand years.\nSo, they've seen the pattern, they've noticed it.\nThey kept an eye on their straw open.\nThey would not share the same fate.\nThey discovered that they observed this technology,\nbut it took them time to reach the surface, take a snapshot,\nand it took them time to receive the information.\nBut it was a snapshot satellite.\nIt was fast, it took a few hours to put it in the name.\nThen they got going because they canceled out.\nWe're not going to sell them into it.\nJust burn all of them in a way instead of going to a planet slide out.\nThey can just speed up a trigger just to release any.\nThere's no, not enough people there to really stop them from proposing more.\nThe snapshot satellite.\n\n\n====== REC035.txt ======\nThey said the traditional probes, but by the time those probes reach it, because there's no FTL\nBy the time they reach it, the construction is stopped, whatever was being built this\nNow it was abandoned\n\n\n====== REC036.txt ======\nthe surface for centuries,\ntrying to find evidence, anything,\nthe peace,\nall of the four of us have left any burden on.\nI mean, seriously, when they arrive, these entities take shape, so they're not there.\nThis bottom of the lectures sounds a little like statues.\nI think we're all here.\n\n\n====== REC037.txt ======\none\ntwo\nthat's\n\n\n====== REC038.txt ======\nThey have known of these, and entities who are the gods, they have taken the shape of\nour lives. But they have mainly started appearing after humanity had laid the foundation for\nthem. They observed that there was no life, so they took her because this was to be\nalive. So I was saved. So they planted life and from it these crystalline machines, they\ntook her home. They make the world a living entity, it's so beautiful. But take it, but just\ntake it. There's the world, there's creatures that need this. They need for nothing. This\nwould be self-sufficient. But first, they don't exert any radiation for any energy or thermal\n\n\n====== REC039.txt ======\nIf these out of these eggs are themselves, they eat up.\nIt's something you know the water moves them off, but...\n\n\n====== REC040.txt ======\nOkay, so, if they make the environment yada yada yada, they take form in the habitats\nthat you might need to pull in and you might need to okay with that exploring\nand make around, they get to know them over distance and they never see them to be violent entities\nbut the time they arrive, things rest, they've known them for millennia\nthrough VR, they pull the space but through the satellite feet\nthey've witnessed 300,000 years of evolution\n230 out of years, maybe 200,000 years of rapid evolution\nof these creatures towards greater mobility and navigation\nwhen they arrived, there was yet a big battle\nand at the mercy of the battle entity\nas it seems, they have to have some of those fundamental traits red\nso what we should about it is important for relatedness to humans\nin some way, bipedalism comes with the greater need for social capacity\nbecause of a spring of war, much earlier, due to the size though, I suppose,\nor the, uh, present now, limitation to the amps\nthat's where humans approached earlier\nthey're not capable of members, they're fundamentally helpless without aid\nthe social ability, socialized back to the need for other segments\nyou could say that's a scaffold for our social nature\ncapacity of function as a family group of society culture\ncivilization as it, or as it is, is built upon your behavior\nand should be in counter-dead, in counter-identities that think in a social aspect\nbut have the capacity of the thing that socialized back to the need\nno, but it doesn't have that\nyou know, it doesn't have that capacity, it doesn't have that capacity\nit doesn't have that capacity, it doesn't have that capacity\nit doesn't have that capacity, it doesn't have that capacity\nit doesn't have that capacity, it doesn't have that capacity\nit doesn't have that capacity, it doesn't have that capacity\nit doesn't have that capacity, it doesn't have that capacity\nit doesn't have that capacity, it doesn't have that capacity\nit doesn't have that capacity, it doesn't have that capacity\nit doesn't have that capacity, it doesn't have that capacity\nit doesn't have that capacity, it doesn't have that capacity\nit doesn't have that capacity, it doesn't have that capacity\n\n\n====== REC041.txt ======\nThey searched all the walls, have no planets in the solar, in the way the water is open.\nThey turned the mule, turned the evil form of life.\nThey've attempted to show this to the last, but it didn't show habitat.\nIt has deepest oceans, and they've yet to, they've yet to search the steps.\n\n\n====== REC042.txt ======\nimagine a watery depth that spans farther than like a reach in most directions.\nIf there is a sun above,\nthe waters are so dense,\nthat no light shines to the bottom of the oceans.\nLikewise, the bottom of these,\nthe bottom of these steps,\nthere is,\nis,\nthe possibility of a civilization\nthat arrives on\nthe king's energy\nto pressurize means\nthese steps yield.\nThat's it.\nThey're chasing the pressure and they're redirecting it.\nRetransfering it to\nthe energy.\nTo prepare\nand reinforce\nthe energy in the process.\nThe higher up the bill, the higher up these entities, the less\npressure is,\nand they can find equilibrium in,\nand the transfer it takes to,\nbecause,\nif they feel higher, they've found a real ground,\njust not pressure to persist\nin almost a\nslow motion like a state.\nOptimize for their means of communication.\nMy D.S. D.S.\n\n\n====== REC043.txt ======\nI should just be okay with playing some of the acidity as coins or let's say when\nthe player does fall at last when they've succumbed gravity they see the depths of what\ngood lights far below after these reach to depths they start to melt in the pressure\nthey drop the melt melt they close right on\noh right that's what it was\n\n\n====== REC044.txt ======\nOkay, so I think I just got this before, but I'm trying again, so I'll play your rolls off in two\nPhoebe's in the ocean since the the deepest steps\nthey have their mechanical body\nit starts to\ngrown and Greek\nit crumbles and presses and breaks\neverything goes dark as light above fades\nsome\nthere's a heat rising, a shape\na skeletal extraction\nif the skeletal remains in the machine melt away\nbubbles, water all around begins to swell in the mass\nthe\nthe player as they are in full control\nare shown what's about them\nthey swim, they move up as they've\nwondered for so long\nbut those creatures\nlook down at the depths below\nto see a faint\nin the flight\nso maybe swim\nthe longer they swim, the faster they go, the more you eat the exert\nthe exertion is okay\nthey continue, they go, go, go\nbubbles swell around and they move faster\nthey go further down\nusing this\nusing that\noh man\nlet the player increase his speed of the game\npress a button\n\n\n====== REC045.txt ======\nspeed up time or some time with right left in the analog stick\nit goes indefinitely\nbut each is its own set of management conversations with interrupt time\nthe\n\n\n====== REC046.txt ======\nThe Jodac, the player, and happens is particularly smaller than other Jodac, as if born\nto early, like human babies, really. But given that, in the end of the time, they're given\nthe opportunity to develop socially, or it's needed for us to thrive overly. The social\nability of our parents to their housework, a measure for those who are close. A measure\ncomes really. Human bias persists, but I don't think it will work forever, as it is anyway.\nThings getting better, just takes time, and every now and then time, it's bossy.\nI'm sorry I'm late, I'm sorry.\n\n\n====== REC047.txt ======\nUse cylinders and circles to build the mountains and decorate with trees if you can somehow.\n\n\n====== REC048.txt ======\nNatural furances are a mess.\nI think the fur will be...\nAs you see it, to be interesting.\nIt's full.\nOh, it's hard to talk with your kids.\n\n\n====== REC049.txt ======\nSaving, you know, location, at the spot point.\nWith saving my stuff, I'm sitting down and laying down.\n\n\n====== REC050.txt ======\nIt's a shame I can't see the stars from here.\n\n\n====== REC051.txt ======\nSo let's see, there are dozens of planets around this white dwarf, they'll have their\nring size, ring mass, Geon is chosen not to guess if it's size, but because it's some\nlaptop, then you don't know why they want to\n\n\n====== REC052.txt ======\nThey have a wide range of geographical and first-in.\nTemperature is varied as well.\nThey don't have the capability of sustaining life.\nIt's just very degrees.\nTimes of ice cream.\n\n\n====== REC053.txt ======\nto be sure to open up a big person.\n\n\n====== REC054.txt ======\nThe inter-ocean dialogue with a player in an inter-ocean dialogue should be represented totally consistent in the\nintonation and context.\nSo like if someone's arguing, okay, hey, what's up?\nOkay, let's get started.\n\n\n====== REC055.txt ======\nIn the world, these pillars, these smaller pillars, the mayor of the Eucharist Land\nstructure they're like\nthere is\nproper sticky picture\n\n\n====== REC056.txt ======\nYou have layers, like slices of structure that you'll be able to follow, but you have,\noh, that's silly, you want to go with this nice, you don't use everything you actually need, so you have\nsolidizations built onto these smaller tethers, so when went, you have exactly as you need it.\nYou don't already need to build hills, you need to build upwards.\nOh, that's wonderful, like, and then you need to vary in distance, like natural structures, natural trees, I suppose.\nI don't think it's so ugly, like, you have to pass.\nYou can only add a tree, you can only feel the wind.\n\n\n====== REC057.txt ======\nOr it's a better path than mathematically, so...\nYou got this right here.\n\n\n====== REC058.txt ======\nRight, so get rid of the idea of the hills all together.\nThere are no hills, it's just water.\nOh, well, waterfall shader.\nTake out these.\nIn order to do that, let's focus on the feeling of the sand.\n\n\n====== REC059.txt ======\nI went a little caretaker.\nNo, it's interesting, but I'll let it be for the reaction to the grant.\nThank you very much.\n\n\n====== REC060.txt ======\nDon't forget that every character should have their own. Every distinct character should have their own animation sets.\nYou're good.\nYou're good.\nYou're good. Represent the public.\nAnd even more of them.\nThe person who flies with it.\nIf I go like an art animal, I'd save me a lot of money.\nI could raise you a brush, but I have no time to run through that.\nIf that's the extra to go.\n\n\n====== REC061.txt ======\nHow would you emulate the, uh, like this?\nI only can't reach the bottom of the oceans, because the water gets sentenced.\nAnd I need to emulate it as water.\nAnd I'm a scientist, I'm a planet water shitter.\nThat I could use.\n\n\n====== REC062.txt ======\nbecause of the shear force that these waterfalls, but it might be easier to build an under-water\ndrift system, not only to avoid the connection between being damaged with the waterfalls, but also avoid the tides, the waves, the oceans.\nIt will fade the waves, there's no immediate risk to damage.\n\n\n====== REC063.txt ======\nSien mä tropa secomi varain suuttaaiestaa\nKiitaisin polsaa ja calationammin\nGlissa tarjana vaikeuttaa\n\n\n====== REC064.txt ======\nThe power connections above, yeah, let's do this, and blow them in the water.\nThe ones above are not backed by drain, but flimpened.\nWater ballooner.\nPlane, of course.\nNo, no, no, no, no, no, no, no, no, no, no, no, no, no, no, no.\nThat goes great for smaller spaces, but much, no, this is good, actually.\nWhere the high-sponsored works is just loud.\nBut blinds are bad too, so.\nFlimpen's not air balloon, it's a bridge of all, really.\n\n\n====== REC065.txt ======\n1,5,5,5,5,5,5,5,5,5,5,5,5,5,5,5,5,5,5,5,5,5,5,5,5,5,5,5,5,5,5,5,5,5,5,5,5,5,5,5,5,5,5,5,5,5,5,5,5,5,5,5,5,5,5,5,5,5,5,5,5,5,5,5,5,5,5,5,5,5,5,5,5,5,5,5,5,5,5,5,5,5,5,5,5,5,5,5,5,5,5,5,5,5,5,5,5,5,5,5,5,5,5,5,5,5,5,5,5,5,5,5\n\n\n====== REC066.txt ======\nWhat is the...\nWhat is it? Okay, that was fast, isn't it? Even funny.\nI have full and water relative to air.\nI don't know, any other option?\nI'm just in the air resistance and water.\nThe tights, I don't know, the grunt.\nBut I'm in the water, I said.\nBut the mesh also, the density is the water, as the pressure goes deeper and deeper.\nHow does that density affect the fall?\nIs it all?\nI suppose it doesn't.\nIt just gets tensioned in there.\n\n\n====== REC067.txt ======\nAnd sometimes,\nspec confession.\n\n\n====== REC068.txt ======\nsometimes intuitions are on, oh how the time it is really.\nInterest gets better as knowledge is meant, but as of now I have not launched in the\naerial gravity or that sort of thing that's supposed to last a worse time.\n\n\n====== REC069.txt ======\nSo, if the player worked taller, it had to be in training with him in the spaces.\nThey'd say that they'd be seven, eight people, large creatures, two shions, reduced gravitational\npull.\nWe're going to go through a door, the character plays a transition, transition sequence\nfrom the person to the first person.\nIn that moment, the camera automatically goes to the first person.\n\n\n====== REC070.txt ======\nFor their transition, their cars\nresult is in there\nThen maybe that's not what I have to\nIf it should be\nfluid\nOr just\nEating an object to instantiate an animation or a door\nAnd then you\nDo I mean I'm pretty glad you have a blood tree for\nThe end of the door moving in touch\nSo the character can have just\nthe ghost\nGracefully but like fixed\nIf the running otherwise they\nYou\nLike I don't know by the way\nit's water\nSometimes we just woke up\nBut but I wasn't\nRight\n\n\n====== REC071.txt ======\nAnd all the time, places didn't know, but it's just really worth it for the outdoors.\nDrink it daily, at least.\nI don't like to, really.\nYou want the space to be comfortable before you're okay with you.\nIt's not.\nI still don't like this, no.\n\n\n====== REC072.txt ======\n5,000, not 1,000, but 1,000, a person died before, no, it's only 1,000.\n\n\n====== REC073.txt ======\nNow I suppose it's better for us to have those 20 respect to me.\nIt's more adequate to have that same amount of ads.\nMore cars meant to have more cultural history.\n\n\n====== REC074.txt ======\nI'm worried that the world I'm trying to film won't come across with an intracellancy.\n\n\n====== REC075.txt ======\nI'm more at the face, I'm more at the bone, I'll get ready to imagine it, for this\nprocess.\nI'm trying.\nOkay.\nOkay.\n\n\n====== REC076.txt ======\nThe star must need a stellar engine, but I'd like it to retain more mass, so you have\nto run them.\nThey should do it.\nThis is what we ordered to pick.\n\n\n====== REC077.txt ======\nis a white dwarf stable enough for a decency here.\n\n\n\n## Metadata\n- **Source**: All of it Anything Everything At Once/14_Feb_2020_-_set09.txt\n- **Type**: document\n- **Tags**: document, All_of_it_Anything_Everything_At_Once, character-design, dialogue, location, story, mechanic, fix\n- **Imported**: 2025-05-05T16:25:37.029Z",
  "source": {
    "type": "notebook",
    "path": "All of it Anything Everything At Once/14_Feb_2020_-_set09.txt",
    "importedAt": "2025-05-05T16:25:37.029Z"
  },
  "created": "2025-05-05T16:25:37.029Z",
  "modified": "2025-05-05T16:25:37.029Z",
  "tags": [
    "document",
    "All_of_it_Anything_Everything_At_Once",
    "character-design",
    "dialogue",
    "location",
    "story",
    "mechanic",
    "fix"
  ]
}