{
  "title": "19_Jul_2020",
  "content": "# 19_Jul_2020\n\nContent-Type: text/x-zim-wiki\nWiki-Format: zim 0.6\nCreation-Date: 2024-07-23T22:27:05-07:00\n\n====== REC002.txt ======\nI think about to think about if you do something about this at home.\nOkay, so here is simply all the ones you have to give.\n1...2...3...\nThat consideration.\nWe are just speaking here...\nI'm going to put it in the middle of the pot and put it in the pot and put it in the pot and put it in the pot and put it in the pot and put it in the pot and put it in the pot and put it in the pot and put it in the pot and put it in the pot and put it in the pot and put it in the pot and put it in the pot and put it in the pot and put it in the pot and put it in the pot and put it in the pot and put it in the pot and put it in the pot and put it in the pot and put it in the pot and put it in the pot and put it in the pot and put it in the pot and put it in the pot and put it in the pot and put it in the pot and put it in the pot and put it in the pot and put it in the pot and put it in the pot and put it in the pot and put it in the pot and put it in the pot and put it in the pot and put it in the pot and\n\n\n====== REC004.txt ======\nI think it's in the video here about these.\nI feel like I'm eating too many memories.\nIn your corner, that's fine.\nWhatever I record, thanks.\nI'm waiting to be done with that.\nI'm just disturbing people.\nThank you.\n\n\n====== REC007.txt ======\nI thought they were giving the time, I could go through them, and talk about it.\nOne of the things that I, at least, transcribes, like I want to,\nwas really getting us out of my...\noutside the old town.\nWhat are you?\nAsparagus...\ncarrot...\nI don't know what it is, I'm just referring to it.\nIt's okay.\nSo this is just speaking, I don't know what the fuck it is.\nThere's no tension on it, I think.\nIt's just you read them.\nWhat the fuck am I talking about?\nWhat the fuck am I talking about?\nWhat am I talking about?\nCurse it.\nCurse it.\nBad, bad.\nCurse it.\nCurse it.\nIt's the words I used to use.\nI used to say words to make it like a fish,\nbut when I was trying to imagine the head,\nI would be able to try to detect it.\nThe image is retained.\nI'm making tension, if I'm aware of it,\nactively engaging with the content of this.\nThis is the description of the world.\nThe characters.\nSorry.\nSorry.\n\n\n====== REC008.txt ======\n1,5,5,5,5,5,5,5,5,5,5,5,5,5,5,5,5,5,5,5,5,5,5,5,5,5,5,5,5,5,5,5,5,5,5,5,5,5,5,5,5,5,5,5,5,5,5,5,5,5,5,5,5,5,5,5,5,5,5,5,5,5,5,5,5,5,5,5,5,5,5,5,5,5,5,5,5,5,5,5,5,5,5,5,5,5,5,5,5,5,5,5,5,5,5,5,5,5,5,5,5,5,5,5,5,5,5,5,5,5,5,5\n\n\n\n## Metadata\n- **Source**: All of it Anything Everything At Once/19_Jul_2020.txt\n- **Type**: document\n- **Tags**: document, All_of_it_Anything_Everything_At_Once, character-design\n- **Imported**: 2025-05-05T16:25:37.034Z",
  "source": {
    "type": "notebook",
    "path": "All of it Anything Everything At Once/19_Jul_2020.txt",
    "importedAt": "2025-05-05T16:25:37.034Z"
  },
  "created": "2025-05-05T16:25:37.034Z",
  "modified": "2025-05-05T16:25:37.034Z",
  "tags": [
    "document",
    "All_of_it_Anything_Everything_At_Once",
    "character-design"
  ]
}