{
  "title": "educator-woker-conditons",
  "content": "# educator-woker-conditons\n\nContent-Type: text/x-zim-wiki\nWiki-Format: zim 0.6\nCreation-Date: 2024-09-23T17:04:58-07:00\n\n====== educator worker conditons ======\nWe're short in every aspect of education.\nEveryone's just stretched thin.\nI mean, we have trash cans that are full of trash\nand not enough custodians to do their jobs.\nI am now the only special ed math teacher in my school.\nFor 20 years, I've lived paycheck to paycheck.\nAnd I know many teachers who have had to have second jobs.\nBut what we've said to teachers is, those are the standards.\nIf you're departing from that and you're teaching kids\nbased on race, you could be disciplined as a result of that.\nBut to actually teach our children that one group is\nadvantaged and another is disadvantaged\nsimply because of the color of their skin cuts across everything\nwe know to be true.\nGovernor Bill Lee has signed a bill that would censor academic discussions\nabout American history, race, and gender in Tennessee classrooms.\nIn our efforts to increase pay, we often hear, well, you know,\neducators should do the work because they love to do the work\nand they want to help kids.\nBut that's an unfair statement to make to expect that, you know,\nwe'll keep piling on, piling on, piling on,\nand be critical at the same time and still expect you to do it for poverty wages.\nOne of the things that the governor has done successfully\nis propose increasing minimum tier salary levels\nand how we structure our pay for educators\nto a much higher level than we've ever seen.\nSo a first year teacher would make $50,000.\nThat's a good wage in New Mexico.\nCertainly it's not the end wage that we'd want to see for folks\nin our schools, but it's a great first step.\nThe average educator now is at 64,000,\nmakes us the highest in the region,\nand that's before we're going to add 7% raises.\nSo having a $15 minimum wage, for example,\nin addition to that 7% is really going to be life changing,\nespecially for hourly educators.\nFunding educators in a way that's dignified\nshould not be a political issue, but it is.\nAnd so depending on who occupies the governor's mansion,\nsome groups shift positions, let's say.\nAnd so this year because the crisis is so bad,\nwe have found sort of strange bedfellows in that sense,\nwhere folks who had not been as enthusiastic\nabout compensation increases or increases\nto health care coverage or pension coverage\nare now suddenly saying these are great ideas.\nThese raises represent the difference\nof being on Medicaid with your family,\nthe difference of having to have a second or third job\nor doing tutoring work on the side,\nthe difference of driving the bus during the day\nand having to take extra routes for extra curriculars\njust to make ends meet.\nSo having these increased compensation flow down to the workers\ngives people dignity.\nIt shows that their work is being respected.\nI think the proposed raises in this year's legislative session\nmean that we are finally going to be competitive\nin this part of the country for people to want to come\nto New Mexico to work and live and play,\nand maybe we'll be able to be a role model\nfor other states surrounding us.\nI can go to Texas, but they tell me\nthat I have to teach history a certain way.\nI can go in Arizona, but you should hear the things\nthat their governor says about teachers.\nArizona kids are going to stay in their classroom\nand we're not going to let the union thugs\nplay Chicago-like games in Arizona.\nAnd then you look at New Mexico and go,\nman, they're paying the same amount.\nThey are actually treated like professionals.\nI think that will help with the shortage.\nBut there's a shortage nationwide.\nWe can't just do this on a New Mexico level.\nEvery state has to do this.\nThis has to be a national movement to get people\nto go back into education.\nThere's work to be done to be clear.\nI mean, we do need to continue to look at adjunct pay\nat higher education institutions.\nWe need to look at increasing our minimum wage over time.\nOur work is not done as far as remaining competitive\nin the long term on salaries for the entire system.\nYour own government.\n\n\n## Metadata\n- **Source**: reference-wiki-pages/educator-woker-conditons.txt\n- **Type**: wiki\n- **Tags**: wiki, reference-wiki-pages, story\n- **Imported**: 2025-05-05T16:25:37.232Z",
  "source": {
    "type": "notebook",
    "path": "reference-wiki-pages/educator-woker-conditons.txt",
    "importedAt": "2025-05-05T16:25:37.232Z"
  },
  "created": "2025-05-05T16:25:37.232Z",
  "modified": "2025-05-05T16:25:37.232Z",
  "tags": [
    "wiki",
    "reference-wiki-pages",
    "story"
  ]
}