{
  "title": "interface-system",
  "content": "# interface-system\n\nContent-Type: text/x-zim-wiki\nWiki-Format: zim 0.6\nCreation-Date: 2024-07-23T16:46:23-07:00\n\n====== interface-system ======\nTo help you design an intuitive navigation system for your mobile application, let's start with some core principles and a basic structure. We'll ensure the navigation is straightforward, efficient, and user-friendly.\nCore Principles\n\n\tSimplicity: Keep navigation options clear and concise.\n\tConsistency: Use familiar icons and patterns across the app.\n\tAccessibility: Ensure all elements are accessible to users with different needs.\n\tFeedback: Provide immediate feedback for user actions.\n\tHierarchy: Maintain a clear hierarchy of information.\n\nBasic Structure\n\n\tBottom Navigation Bar:\n\t\tHome: Central hub with the most important and frequently accessed features.\n\t\tSearch: A dedicated search feature to quickly find content.\n\t\tNotifications: Access to alerts, updates, and notifications.\n\t\tProfile: User profile and settings.\n\n\tSide Menu (Hamburger Menu):\n\t\tAdditional sections or less frequently accessed features.\n\t\tLinks to support, FAQs, and other resources.\n\n\tTab Navigation:\n\t\tUse for content-heavy sections within the app (e.g., categories within the home screen).\n\n\tFloating Action Button (FAB):\n\t\tFor primary actions like adding new content or starting a new task.\n\nDetailed Design\nBottom Navigation Bar\n\n\tIcons and Labels: Use intuitive icons with labels for each tab. For example, a house icon for Home, a magnifying glass for Search, a bell for Notifications, and a user silhouette for Profile.\n\tHighlight Active Tab: Highlight the active tab with a different color or underline.\n\tBadge Notifications: Display notification badges on icons when there are updates.\n\nSide Menu (Hamburger Menu)\n\n\tExpandable Sections: Group related items into expandable sections to keep the menu tidy.\n\tUser Info: Display basic user information (name, profile picture) at the top.\n\tSupport Links: Include links to support, FAQs, terms of service, and other resources.\n\nTab Navigation\n\n\tSwipe Gestures: Allow users to swipe between tabs for easier navigation.\n\tConsistent Design: Ensure each tab follows a consistent design pattern to avoid confusion.\n\nFloating Action Button (FAB)\n\n\tPrimary Action: Use for the most important action in the app, such as adding new content.\n\tContextual: Change the action based on the current screen's context.\n\nPrototyping\n\n\tWireframe Sketches: Start with wireframe sketches of each screen to map out the navigation flow.\n\tInteractive Prototype: Create an interactive prototype using tools like Figma or Adobe XD to test the navigation flow.\n\tUser Testing: Conduct user testing sessions to gather feedback and identify pain points.\n\nExample Flow\n\n\tHome Screen:\n\t\tMain content area with shortcuts to key sections.\n\t\tBottom navigation bar for primary sections.\n\n\tSearch Screen:\n\t\tSearch bar at the top.\n\t\tRecent searches and suggested content below.\n\n\tNotifications Screen:\n\t\tList of notifications with icons indicating the type of notification.\n\t\tOption to mark all as read.\n\n\tProfile Screen:\n\t\tUser information at the top.\n\t\tSettings and preferences below.\n\n\tSide Menu:\n\t\tUser profile and quick actions at the top.\n\t\tExpandable sections for additional features like settings, help, and feedback.\n\nBy following these guidelines, you can create an intuitive navigation system that enhances the user experience and makes your mobile application easy to use. Let me know if you need specific mockups or further details on any part of the design!\n\n\n## Metadata\n- **Source**: All of it Anything Everything At Once/interface-system.txt\n- **Type**: document\n- **Tags**: document, All_of_it_Anything_Everything_At_Once, item, feature\n- **Imported**: 2025-05-05T16:25:37.142Z",
  "source": {
    "type": "notebook",
    "path": "All of it Anything Everything At Once/interface-system.txt",
    "importedAt": "2025-05-05T16:25:37.142Z"
  },
  "created": "2025-05-05T16:25:37.142Z",
  "modified": "2025-05-05T16:25:37.142Z",
  "tags": [
    "document",
    "All_of_it_Anything_Everything_At_Once",
    "item",
    "feature"
  ]
}