{
  "title": "On_Command_VO",
  "content": "# On_Command_VO\n\nContent-Type: text/x-zim-wiki\nWiki-Format: zim 0.6\nCreation-Date: 2025-03-10T16:11:31-07:00\n\n====== On Command VO ======\n# Player VO\n- Carden Frode VO - Loyal\n- Kalisa Bast VO - Calm\n- Marian Cenric VO - Caring\n- Sorrel Amor VO - Optimistic\n- Wilmet Edith VO - Reliable\n- Arrisi Kron VO - Determined\n- Gregers Ovesen VO - Fearless\n- Josefine \"Jo\" Strand VO - Adventurous\n- Lorens Nass VO - Capable\n- Vivian Holt VO - Confident\n- Oskidere \"Oski\" VO - Calculating\n\n# Stratetic Point VO\n- Assign SP - Carden\n- Assign SP - Kalisa\n- Assign SP - Marian\n- Assign SP - Sorrel\n- Assign SP - Wilmet\n- Assign SP - Arrisi\n- Assign SP - Gregers\n- Assign SP - Jo\n- Assign SP - Lorens\n- Assign SP - Vivian\n- Assign SP - Oski\n\n# Assign SP Dialogues\n- Carden: \"Set up there, Sentinel.\"\n- Kalisa: \"Taking cover!\"\n- Marian: \"Uh huh.\"\n- Sorrel: \"Ok!\"\n- Wilmet: \"Gotcha, boss.\"\n- Arrisi: \"Affirmative.\"\n- Gregers: \"Moving now.\"\n- Jo: \"I'll do it.\"\n- Lorens: \"Got it!\"\n- Vivian: \"Haha, alright.\"\n- Oski: \"No problem! Where? Oh.\"\n\n# More Dialogues\n- Carden: \"X, give us some covering fire.\"\n- Kalisa: \"On it!\"\n- Marian: \"Alright.\"\n- Sorrel: \"I'll be there!\"\n- Wilmet: \"On my way!\"\n- Arrisi: \"Right away, sir!\"\n- Gregers: \"Right.\"\n- Jo: \"Moving.\"\n- Lorens: \"Sure thing!\"\n- Vivian: \"If you say so.\"\n- Oski: \"Fine with me! On route!\"\n\n- Carden: \"We'll take them down from here.\"\n- Kalisa: \"Right on!\"\n- Marian: \"My pleasure.\"\n- Sorrel: \"Can do!\"\n- Wilmet: \"I'm in position.\"\n- Arrisi: \"Roger that.\"\n- Gregers: \"Taking position.\"\n- Jo: \"On point.\"\n- Lorens: \"You got it!\"\n- Vivian: \"Only 'cause you asked nice.\"\n- Oski: \"Absolutely. Locating!\"\n\n- Carden: \"Let's take 'em out from here.\"\n- Kalisa: \n- Marian: \n- Sorrel: \n- Wilmet: \n- Arrisi: \n- Gregers: \n- Jo: \n- Lorens: \n- Vivian: \n- Oski: \n\n- Carden: \"Make use of this clear line of fire.\"\n- Kalisa: \n- Marian: \n- Sorrel: \n- Wilmet: \n- Arrisi: \n- Gregers: \n- Jo: \n- Lorens: \n- Vivian: \n- Oski: \n\n# Unassign SP\n- Unassign SP - Carden\n- Unassign SP - Kalisa\n- Unassign SP - Marian\n- Unassign SP - Sorrel\n- Unassign SP - Wilmet\n- Unassign SP - Arrisi\n- Unassign SP - Gregers\n- Unassign SP - Jo\n- Unassign SP - Lorens\n- Unassign SP - Vivian\n- Unassign SP - Oski\n\n# Unassign SP Dialogues\n- Carden: \"Pack it up, Sentinel.\"\n- Kalisa: \n- Marian: \n- Sorrel: \n- Wilmet: \n- Arrisi: \n- Gregers: \n- Jo: \n- Lorens: \n- Vivian: \n- Oski: \n\n- Carden: \"Ignore that order.\"\n- Kalisa: \n- Marian: \n- Sorrel: \n- Wilmet: \n- Arrisi: \n- Gregers: \n- Jo: \n- Lorens: \n- Vivian: \n- Oski: \n\n- Carden: \"Sentinel, abandon position.\"\n- Kalisa: \n- Marian: \n- Sorrel: \n- Wilmet: \n- Arrisi: \n- Gregers: \n- Jo: \n- Lorens: \n- Vivian: \n- Oski: \n\n- Carden: \"Nevermind, X.\"\n- Kalisa: \n- Marian: \n- Sorrel: \n- Wilmet: \n- Arrisi: \n- Gregers: \n- Jo: \n- Lorens: \n- Vivian: \n- Oski: \n\n- Carden: \"Disregard that command.\"\n- Kalisa: \n- Marian: \n- Sorrel: \n- Wilmet: \n- Arrisi: \n- Gregers: \n- Jo: \n- Lorens: \n- Vivian: \n- Oski: \n\n# Unassign All SP\n- Unassign All SP - Carden\n- Unassign All SP - Kalisa\n- Unassign All SP - Marian\n- Unassign All SP - Sorrel\n- Unassign All SP - Wilmet\n- Unassign All SP - Arrisi\n- Unassign All SP - Gregers\n- Unassign All SP - Jo\n- Unassign All SP - Lorens\n- Unassign All SP - Vivian\n- Unassign All SP - Oski\n\n# Unassign All SP Dialogues\n- Carden: \"Sentinels, regroup.\"\n- Kalisa: \n- Marian: \n- Sorrel: \n- Wilmet: \n- Arrisi: \n- Gregers: \n- Jo: \n- Lorens: \n- Vivian: \n- Oski: \n\n- Carden: \"Form up, squad.\"\n- Kalisa: \n- Marian: \n- Sorrel: \n- Wilmet: \n- Arrisi: \n- Gregers: \n- Jo: \n- Lorens: \n- Vivian: \n- Oski: \n\n- Carden: \"Let's move on.\"\n- Kalisa: \n- Marian: \n- Sorrel: \n- Wilmet: \n- Arrisi: \n- Gregers: \n- Jo: \n- Lorens: \n- Vivian: \n- Oski: \n\n# Unassign All SP Urgent\n- Unassign All SP Urgent - Carden\n- Unassign All SP Urgent - Kalisa\n- Unassign All SP Urgent - Marian\n- Unassign All SP Urgent - Sorrel\n- Unassign All SP Urgent - Wilmet\n- Unassign All SP Urgent - Arrisi\n- Unassign All SP Urgent - Gregers\n- Unassign All SP Urgent - Jo\n- Unassign All SP Urgent - Lorens\n- Unassign All SP Urgent - Vivian\n- Unassign All SP Urgent - Oski\n\n# Fortify SP\n- Fortify SP - Carden\n- Fortify SP - Kalisa\n- Fortify SP - Marian\n- Fortify SP - Sorrel\n- Fortify SP - Wilmet\n- Fortify SP - Arrisi\n- Fortify SP - Gregers\n- Fortify SP - Jo\n- Fortify SP - Lorens\n- Fortify SP - Vivian\n- Fortify SP - Oski\n\n# Emplacement Zone VO\n- Emplacement Zone VO\n- Emplacement Zone VO\n- Emplacement Zone VO\n- Emplacement Zone VO\n- Emplacement Zone VO\n- Emplacement Zone VO\n- Emplacement Zone VO\n- Emplacement Zone VO\n- Emplacement Zone VO\n- Emplacement Zone VO\n- Emplacement Zone VO\n- Emplacement Zone VO\n\n# Setup EZ\n- Setup EZ - Carden\n- Setup EZ - Kalisa\n- Setup EZ - Marian\n- Setup EZ - Sorrel\n- Setup EZ - Wilmet\n- Setup EZ - Arrisi\n- Setup EZ - Gregers\n- Setup EZ - Jo\n- Setup EZ - Lorens\n- Setup EZ - Vivian\n- Setup EZ - Oski\n\n# Fortify EZ\n- Fortify EZ - Carden\n- Fortify EZ - Kalisa\n- Fortify EZ - Marian\n- Fortify EZ - Sorrel\n- Fortify EZ - Wilmet\n- Fortify EZ - Arrisi\n- Fortify EZ - Gregers\n- Fortify EZ - Jo\n- Fortify EZ - Lorens\n- Fortify EZ - Vivian\n- Fortify EZ - Oski\n\n# Destroy EZ\n- Destroy EZ - Carden\n- Destroy EZ - Kalisa\n- Destroy EZ - Marian\n- Destroy EZ - Sorrel\n- Destroy EZ - Wilmet\n- Destroy EZ - Arrisi\n- Destroy EZ - Gregers\n- Destroy EZ - Jo\n- Destroy EZ - Lorens\n- Destroy EZ - Vivian\n- Destroy EZ - Oski\n\n# Squad Feedback VO\n- Squad Feedback VO\n- Squad Feedback VO\n- Squad Feedback VO\n- Squad Feedback VO\n- Squad Feedback VO\n- Squad Feedback VO\n- Squad Feedback VO\n- Squad Feedback VO\n- Squad Feedback VO\n- Squad Feedback VO\n- Squad Feedback VO\n- Squad Feedback VO\n\n# Player Killed Enemy\n- Player Killed Enemy - Carden\n- Player Killed Enemy - Kalisa\n- Player Killed Enemy - Marian\n- Player Killed Enemy - Sorrel\n- Player Killed Enemy - Wilmet\n- Player Killed Enemy - Arrisi\n- Player Killed Enemy - Gregers\n- Player Killed Enemy - Jo\n- Player Killed Enemy - Lorens\n- Player Killed Enemy - Vivian\n- Player Killed Enemy - Oski\n\n# NPC Killed Enemy\n- NPC Killed Enemy - Carden\n- NPC Killed Enemy - Kalisa\n- NPC Killed Enemy - Marian\n- NPC Killed Enemy - Sorrel\n- NPC Killed Enemy - Wilmet\n- NPC Killed Enemy - Arrisi\n- NPC Killed Enemy - Gregers\n- NPC Killed Enemy - Jo\n- NPC Killed Enemy - Lorens\n- NPC Killed Enemy - Vivian\n- NPC Killed Enemy - Oski\n\n# Gyre Spotted\n- Gyre Spotted - Carden\n- Gyre Spotted - Kalisa\n- Gyre Spotted - Marian\n- Gyre Spotted - Sorrel\n- Gyre Spotted - Wilmet\n- Gyre Spotted - Arrisi\n- Gyre Spotted - Gregers\n- Gyre Spotted - Jo\n- Gyre Spotted - Lorens\n- Gyre Spotted - Vivian\n- Gyre Spotted - Oski\n\n# Ultra Gyre Spotted\n- Ultra Gyre Spotted - Carden\n- Ultra Gyre Spotted - Kalisa\n- Ultra Gyre Spotted - Marian\n- Ultra Gyre Spotted - Sorrel\n- Ultra Gyre Spotted - Wilmet\n- Ultra Gyre Spotted - Arrisi\n- Ultra Gyre Spotted - Gregers\n- Ultra Gyre Spotted - Jo\n- Ultra Gyre Spotted - Lorens\n- Ultra Gyre Spotted - Vivian\n- Ultra Gyre Spotted - Oski\n\n# Dredge Spotted\n- Dredge Spotted - Carden\n- Dredge Spotted - Kalisa\n- Dredge Spotted - Marian\n- Dredge Spotted - Sorrel\n- Dredge Spotted - Wilmet\n- Dredge Spotted - Arrisi\n- Dredge Spotted - Gregers\n- Dredge Spotted - Jo\n- Dredge Spotted - Lorens\n- Dredge Spotted - Vivian\n- Dredge Spotted - Oski\n\n# Dredge Spotted Dialogues\n- Carden: \"Sir, we've got a Dredge headed our way!\"\n- Kalisa: \"Dredge! I'll crush it before it crushes us.\"\n- Marian: \"Dredge! Don't let it hit anyone, lead!\"\n- Sorrel: \"Dredge!? Oh, c'mon, I like my spot!\"\n- Wilmet: \"Dredge! Be ready to move!\"\n- Arrisi: \"We've got a Dredge. Don't let it advance!\"\n- Gregers: \"Dredge incoming, boss. Should I stay here?\"\n- Jo: \"It's one of those bulldozers! Can I break it?\"\n- Lorens: \"If that Dredge hits me, you're to blame, Chief.\"\n- Vivian: \n- Oski: \"Enemy Dredge, please don't let it crush me.\"\n\n- Carden: \"Dredge! Are we switching cover, sir?!\"\n- Kalisa: \"That Dredge ain't taking my cover. No way.\"\n- Marian: \"If that Dredge gets near us, move back!\"\n- Sorrel: \"Nope. Not letting that Dredge flatten me.\"\n- Wilmet: \"Fall back if that Dredge gets too close!\"\n- Arrisi: \"Take note of nearby cover! We've got a Dredge!\"\n- Gregers: \"Got a Dredge, boss. Might have to switch cover.\"\n- Jo: \"Dredge! Does, anyone else want to ride one?\"\n- Lorens: \"Hey, Chief. Should I move? I see a Dredge.\"\n- Vivian: \n- Oski: \"Hostile Dredge! Can I fall back, sir?\"\n\n# Scope Spotted\n- Scope Spotted - Carden\n- Scope Spotted - Kalisa\n- Scope Spotted - Marian\n- Scope Spotted - Sorrel\n- Scope Spotted - Wilmet\n- Scope Spotted - Arrisi\n- Scope Spotted - Gregers\n- Scope Spotted - Jo\n- Scope Spotted - Lorens\n- Scope Spotted - Vivian\n- Scope Spotted - Oski\n\n# Siphon Spotted\n- Siphon Spotted - Carden\n- Siphon Spotted - Kalisa\n- Siphon Spotted - Marian\n- Siphon Spotted - Sorrel\n- Siphon Spotted - Wilmet\n- Siphon Spotted - Arrisi\n- Siphon Spotted - Gregers\n- Siphon Spotted - Jo\n- Siphon Spotted - Lorens\n- Siphon Spotted - Vivian\n- Siphon Spotted - Oski\n\n# Siren Spotted\n- Siren Spotted - Carden\n- Siren Spotted - Kalisa\n- Siren Spotted - Marian\n- Siren Spotted - Sorrel\n- Siren Spotted - Wilmet\n- Siren Spotted - Arrisi\n- Siren Spotted - Gregers\n- Siren Spotted - Jo\n- Siren Spotted - Lorens\n- Siren Spotted - Vivian\n- Siren Spotted - Oski\n\n# Vector Spotted\n- Vector Spotted - Carden\n- Vector Spotted - Kalisa\n- Vector Spotted - Marian\n- Vector Spotted - Sorrel\n- Vector Spotted - Wilmet\n- Vector Spotted - Arrisi\n- Vector Spotted - Gregers\n- Vector Spotted - Jo\n- Vector Spotted - Lorens\n- Vector Spotted - Vivian\n- Vector Spotted - Oski\n\n# Soldier Spotted\n- Soldier Spotted - Carden\n- Soldier Spotted - Kalisa\n- Soldier Spotted - Marian\n- Soldier Spotted - Sorrel\n- Soldier Spotted - Wilmet\n- Soldier Spotted - Arrisi\n- Soldier Spotted - Gregers\n- Soldier Spotted - Jo\n- Soldier Spotted - Lorens\n- Soldier Spotted - Vivian\n- Soldier Spotted - Oski\n\n# Reloading\n- Reloading - Carden\n- Reloading - Kalisa\n- Reloading - Marian\n- Reloading - Sorrel\n- Reloading - Wilmet\n- Reloading - Arrisi\n- Reloading - Gregers\n- Reloading - Jo\n- Reloading - Lorens\n- Reloading - Vivian\n- Reloading - Oski\n\n# Low Armor\n- Low Armor - Carden\n- Low Armor - Kalisa\n- Low Armor - Marian\n- Low Armor - Sorrel\n- Low Armor - Wilmet\n- Low Armor - Arrisi\n- Low Armor - Gregers\n- Low Armor - Jo\n- Low Armor - Lorens\n- Low Armor - Vivian\n- Low Armor - Oski\n\n# Low Armor Urgent\n- Low Armor Urgent - Carden\n- Low Armor Urgent - Kalisa\n- Low Armor Urgent - Marian\n- Low Armor Urgent - Sorrel\n- Low Armor Urgent - Wilmet\n- Low Armor Urgent - Arrisi\n- Low Armor Urgent - Gregers\n- Low Armor Urgent - Jo\n- Low Armor Urgent - Vivian\n- Low Armor Urgent - Oski\n\n# Friendly Fire\n- Friendly Fire - Carden\n- Friendly Fire - Kalisa\n- Friendly Fire - Marian\n- Friendly Fire - Sorrel\n- Friendly Fire - Wilmet\n- Friendly Fire - Arrisi\n- Friendly Fire - Gregers\n- Friendly Fire - Jo\n- Friendly Fire - Lorens\n- Friendly Fire - Vivian\n- Friendly Fire - Oski\n\n# Player AFK\n- Player AFK - Carden\n- Player AFK - Kalisa\n- Player AFK - Marian\n- Player AFK - Sorrel\n- Player AFK - Wilmet\n- Player AFK - Arrisi\n- Player AFK - Gregers\n- Player AFK - Jo\n- Player AFK - Lorens\n- Player AFK - Vivian\n- Player AFK - Oski\n\n# Player Misfiring\n- Player Misfiring - Carden\n- Player Misfiring - Kalisa\n- Player Misfiring - Marian\n- Player Misfiring - Sorrel\n- Player Misfiring - Wilmet\n- Player Misfiring - Arrisi\n- Player Misfiring - Gregers\n- Player Misfiring - Jo\n- Player Misfiring - Lorens\n- Player Misfiring - Vivian\n- Player Misfiring - Oski\n\n# Squad Abandoned\n- Squad Abandoned - Carden\n- Squad Abandoned - Kalisa\n- Squad Abandoned - Marian\n- Squad Abandoned - Sorrel\n- Squad Abandoned - Wilmet\n- Squad Abandoned - Arrisi\n- Squad Abandoned - Gregers\n- Squad Abandoned - Jo\n- Squad Abandoned - Lorens\n- Squad Abandoned - Vivian\n- Squad Abandoned - Oski\n\n# Squad Abandoned Urgent\n- Squad Abandoned Urgent - Carden\n- Squad Abandoned Urgent - Kalisa\n- Squad Abandoned Urgent - Marian\n- Squad Abandoned Urgent - Sorrel\n- Squad Abandoned Urgent - Wilmet\n- Squad Abandoned Urgent - Arrisi\n- Squad Abandoned Urgent - Gregers\n- Squad Abandoned Urgent - Jo\n- Squad Abandoned Urgent - Lorens\n- Squad Abandoned Urgent - Vivian\n- Squad Abandoned Urgent - Oski\n\n# Invalid Command\n- Invalid Command - Carden\n- Invalid Command - Kalisa\n- Invalid Command - Marian\n- Invalid Command - Sorrel\n- Invalid Command - Wilmet\n- Invalid Command - Arrisi\n- Invalid Command - Gregers\n- Invalid Command - Jo\n- Invalid Command - Lorens\n- Invalid Command - Vivian\n- Invalid Command - Oski\n\n# Player Blocking Way\n- Player Blocking Way - Carden\n- Player Blocking Way - Kalisa\n- Player Blocking Way - Marian\n- Player Blocking Way - Sorrel\n- Player Blocking Way - Wilmet\n- Player Blocking Way - Arrisi\n- Player Blocking Way - Gregers\n- Player Blocking Way - Jo\n- Player Blocking Way - Lorens\n- Player Blocking Way - Vivian\n- Player Blocking Way - Oski\n\n# Terminal Slice VO\n- Slice Terminal - Carden\n- Slice Terminal - Kalisa\n- Slice Terminal - Marian\n- Slice Terminal - Sorrel\n- Slice Terminal - Wilmet\n- Slice Terminal - Arrisi\n- Slice Terminal - Gregers\n- Slice Terminal - Jo\n- Slice Terminal - Lorens\n- Slice Terminal - Vivian\n- Slice Terminal - Oski\n\n# Cancel Slice Terminal\n- Cancel Slice Terminal - Carden\n- Cancel Slice Terminal - Kalisa\n- Cancel Slice Terminal - Marian\n- Cancel Slice Terminal - Sorrel\n- Cancel Slice Terminal - Wilmet\n- Cancel Slice Terminal - Arrisi\n- Cancel Slice Terminal - Gregers\n- Cancel Slice Terminal - Jo\n- Cancel Slice Terminal - Lorens\n- Cancel Slice Terminal - Vivian\n- Cancel Slice Terminal - Oski\n\n# Terminal Slice Status\n- Terminal Slice Status - Carden\n- Terminal Slice Status - Kalisa\n- Terminal Slice Status - Marian\n- Terminal Slice Status - Sorrel\n- Terminal Slice Status - Wilmet\n- Terminal Slice Status - Arrisi\n- Terminal Slice Status - Gregers\n- Terminal Slice Status - Jo\n- Terminal Slice Status - Lorens\n- Terminal Slice Status - Vivian\n- Terminal Slice Status - Oski\n\n# Terminal Slice Complete\n- Terminal Slice Complete - Carden\n- Terminal Slice Complete - Kalisa\n- Terminal Slice Complete - Marian\n- Terminal Slice Complete - Sorrel\n- Terminal Slice Complete - Wilmet\n- Terminal Slice Complete - Arrisi\n- Terminal Slice Complete - Gregers\n- Terminal Slice Complete - Jo\n- Terminal Slice Complete - Lorens\n- Terminal Slice Complete - Vivian\n- Terminal Slice Complete - Oski\n\n# Door Slice VO\n- Slice Door - Carden\n- Slice Door - Kalisa\n- Slice Door - Marian\n- Slice Door - Sorrel\n- Slice Door - Wilmet\n- Slice Door - Arrisi\n- Slice Door - Gregers\n- Slice Door - Jo\n- Slice Door - Lorens\n- Slice Door - Vivian\n- Slice Door - Oski\n\n# Door Slice Dialogues\n- Carden: \"Let's do this quietly.\"\n- Kalisa: \"Slice that door, Sentinel.\"\n- Marian: \"Let's slice our way in.\"\n- Sorrel: \"Get that door sliced.\"\n- Wilmet: \"Unlock that door.\"\n- Arrisi: \n- Gregers: \n- Jo: \n- Lorens: \n- Vivian: \n- Oski: \n\n# Cancel Door Slice\n- Cancel Door Slice - Carden\n- Cancel Door Slice - Kalisa\n- Cancel Door Slice - Marian\n- Cancel Door Slice - Sorrel\n- Cancel Door Slice - Wilmet\n- Cancel Door Slice - Arrisi\n- Cancel Door Slice - Gregers\n- Cancel Door Slice - Jo\n- Cancel Door Slice - Lorens\n- Cancel Door Slice - Vivian\n- Cancel Door Slice - Oski\n\n# Door Slice Status\n- Door Slice Status - Carden\n- Door Slice Status - Kalisa\n- Door Slice Status - Marian\n- Door Slice Status - Sorrel\n- Door Slice Status - Wilmet\n- Door Slice Status - Arrisi\n- Door Slice Status - Gregers\n- Door Slice Status - Jo\n- Door Slice Status - Lorens\n- Door Slice Status - Vivian\n- Door Slice Status - Oski\n\n# Door Slice Complete\n- Door Slice Complete - Carden\n- Door Slice Complete - Kalisa\n- Door Slice Complete - Marian\n- Door Slice Complete - Sorrel\n- Door Slice Complete - Wilmet\n- Door Slice Complete - Arrisi\n- Door Slice Complete - Gregers\n- Door Slice Complete - Jo\n- Door Slice Complete - Lorens\n- Door Slice Complete - Vivian\n- Door Slice Complete - Oski\n\n# Door Slice Complete Dialogues\n- Carden: \n- Kalisa: \n- Marian: \n- Sorrel: \n- Wilmet: \n- Arrisi: \n- Gregers: \n- Jo: \n- Lorens: \"Oh, so that's how it opens?\"\n- Vivian: \n- Oski: \n\n# Breaching VO\n- Breach Door - Carden\n- Breach Door - Kalisa\n- Breach Door - Marian\n- Breach Door - Sorrel\n- Breach Door - Wilmet\n- Breach Door - Arrisi\n- Breach Door - Gregers\n- Breach Door - Jo\n- Breach Door - Lorens\n- Breach Door - Vivian\n- Breach Door - Oski\n\n# Cancel Door Breach\n- Cancel Door Breach - Carden\n- Cancel Door Breach - Kalisa\n- Cancel Door Breach - Marian\n- Cancel Door Breach - Sorrel\n- Cancel Door Breach - Wilmet\n- Cancel Door Breach - Arrisi\n- Cancel Door Breach - Gregers\n- Cancel Door Breach - Jo\n- Cancel Door Breach - Lorens\n- Cancel Door Breach - Vivian\n- Cancel Door Breach - Oski\n\n# Breach Armed\n- Breach Charge Armed - Carden\n- Breach Charge Armed - Kalisa\n- Breach Charge Armed - Marian\n- Breach Charge Armed - Sorrel\n- Breach Charge Armed - Wilmet\n- Breach Charge Armed - Arrisi\n- Breach Charge Armed - Gregers\n- Breach Charge Armed - Jo\n- Breach Charge Armed - Lorens\n- Breach Charge Armed - Vivian\n- Breach Charge Armed - Oski\n\n# Breach Detonation\n- Detonation Reaction - Carden\n- Detonation Reaction - Kalisa\n- Detonation Reaction - Marian\n- Detonation Reaction - Sorrel\n- Detonation Reaction - Wilmet\n- Detonation Reaction - Arrisi\n- Detonation Reaction - Gregers\n- Detonation Reaction - Jo\n- Detonation Reaction - Lorens\n- Detonation Reaction - Vivian\n- Detonation Reaction - Oski\n\n# Set Charge VO\n- Set Charge - Carden\n- Set Charge - Kalisa\n- Set Charge - Marian\n- Set Charge - Sorrel\n- Set Charge - Wilmet\n- Set Charge - Arrisi\n- Set Charge - Gregers\n- Set Charge - Jo\n- Set Charge - Lorens\n- Set Charge - Vivian\n- Set Charge - Oski\n\n# Charge Status\n- Charge Status - Carden\n- Charge Status - Kalisa\n- Charge Status - Marian\n- Charge Status - Sorrel\n- Charge Status - Wilmet\n- Charge Status - Arrisi\n- Charge Status - Gregers\n- Charge Status - Jo\n- Charge Status - Lorens\n- Charge Status - Vivian\n- Charge Status - Oski\n\n# Cancel Charge\n- Cancel Charge - Carden\n- Cancel Charge - Kalisa\n- Cancel Charge - Marian\n- Cancel Charge - Sorrel\n- Cancel Charge - Wilmet\n- Cancel Charge - Arrisi\n- Cancel Charge - Gregers\n- Cancel Charge - Jo\n- Cancel Charge - Lorens\n- Cancel Charge - Vivian\n- Cancel Charge - Oski\n\n# Change Armed\n- Change Armed - Carden\n- Change Armed - Kalisa\n- Change Armed - Marian\n- Change Armed - Sorrel\n- Change Armed - Wilmet\n- Change Armed - Arrisi\n- Change Armed - Gregers\n- Change Armed - Jo\n- Change Armed - Lorens\n- Change Armed - Vivian\n- Change Armed - Oski\n\n# Detonate Charge & Reaction\n- Detonate Charge - Carden\n- Detonate Charge - Kalisa\n- Detonate Charge - Marian\n- Detonate Charge - Sorrel\n- Detonate Charge - Wilmet\n- Detonate Charge - Arrisi\n- Detonate Charge - Gregers\n- Detonate Charge - Jo\n- Detonate Charge - Lorens\n- Detonate Charge - Vivian\n- Detonate Charge - Oski\n\n# Detonate Charge & Reaction Dialogues\n- Carden: \"Get clear!\"\n- Kalisa: \"Stand back, squad!\"\n- Marian: \"Move aside!\"\n- Sorrel: \"Get back, squad!\"\n- Wilmet: \"Take cover!\"\n- Arrisi: \n- Gregers: \n- Jo: \n- Lorens: \n- Vivian: \n- Oski: \n\n# Resupply VO\n- Resupply - Carden\n- Resupply - Kalisa\n- Resupply - Marian\n- Resupply - Sorrel\n- Resupply - Wilmet\n- Resupply - Arrisi\n- Resupply - Gregers\n- Resupply - Jo\n- Resupply - Lorens\n- Resupply - Vivian\n- Resupply - Oski\n\n# Cancel Resupply\n- Cancel Resupply - Carden\n- Cancel Resupply - Kalisa\n- Cancel Resupply - Marian\n- Cancel Resupply - Sorrel\n- Cancel Resupply - Wilmet\n- Cancel Resupply - Arrisi\n- Cancel Resupply - Gregers\n- Cancel Resupply - Jo\n- Cancel Resupply - Lorens\n- Cancel Resupply - Vivian\n- Cancel Resupply - Oski\n\n# Resupply Complete\n- Resupply Complete - Carden\n- Resupply Complete - Kalisa\n- Resupply Complete - Marian\n- Resupply Complete - Sorrel\n- Resupply Complete - Wilmet\n- Resupply Complete - Arrisi\n- Resupply Complete - Gregers\n- Resupply Complete - Jo\n- Resupply Complete - Lorens\n- Resupply Complete - Vivian\n- Resupply Complete - Oski\n\n# No Resupply Needed\n- No Resupply Needed - Carden\n- No Resupply Needed - Kalisa\n- No Resupply Needed - Marian\n- No Resupply Needed - Sorrel\n- No Resupply Needed - Wilmet\n- No Resupply Needed - Arrisi\n- No Resupply Needed - Gregers\n- No Resupply Needed - Jo\n- No Resupply Needed - Lorens\n- No Resupply Needed - Vivian\n- No Resupply Needed - Oski\n\n# Revive VO\n- Revive - Carden\n- Revive - Kalisa\n- Revive - Marian\n- Revive - Sorrel\n- Revive - Wilmet\n- Revive - Arrisi\n- Revive - Gregers\n- Revive - Jo\n- Revive - Lorens\n- Revive - Vivian\n- Revive - Oski\n\n# Cancel Revive\n- Cancel Revive - Carden\n- Cancel Revive - Kalisa\n- Cancel Revive - Marian\n- Cancel Revive - Sorrel\n- Cancel Revive - Wilmet\n- Cancel Revive - Arrisi\n- Cancel Revive - Gregers\n- Cancel Revive - Jo\n- Cancel Revive - Lorens\n- Cancel Revive - Vivian\n- Cancel Revive - Oski\n\n# Exception Dialogues\n- Sorrel: \"I'm sorry, sir. But I can't wait to help him.\"\n- Marian: \"FUCK YOU. I'm helping her.\"\n- Kalisa: \"Huh? You can't make me do that, sir.\"\n- Carden: \"What?! No can do, sir. I'm helping him now.\"\n- Jo: \"Not gonna happen, sir. I can't lose her too!\"\n- Gregers: \"You jerk! I'm helping him anyway!\"\n- Oski: \"No! They'll kill Oski if I don't help him!\"\n- Vivian: \"Ignoring order, sir. I'm coming, Vivian!\"\n\n# Revive Complete\n- Revive Complete - Carden\n- Revive Complete - Kalisa\n- Revive Complete - Marian\n- Revive Complete - Sorrel\n- Revive Complete - Wilmet\n- Revive Complete - Arrisi\n- Revive Complete - Gregers\n- Revive Complete - Jo\n- Revive Complete - Lorens\n- Revive Complete - Vivian\n- Revive Complete - Oski\n\n# Revive Complete Dialogues\n- Carden: \"That feels so much better.\"\n- Kalisa: \"Ready to smash some droids, sir.\"\n- Marian: \"What a relief.\"\n- Sorrel: \n- Wilmet: \"I'm back on my feet, sir.\"\n- Arrisi: \"I'm recovered, sir.\"\n- Gregers: \"I can move again, thanks!\"\n- Jo: \n- Lorens: \"I've got some armor now, sir!\"\n- Vivian: \"Those droids are gonna regret not killing me.\"\n- Oski: \n- Lorens: \"Partially armored. I'm good to go, lead.\"\n- Vivian: \"Partial armor restored, lead.\"\n\n# Squad Downed\n\n# Player Downed\n- Player Downed - Carden\n- Player Downed - Kalisa\n- Player Downed - Marian\n- Player Downed - Sorrel\n- Player Downed - Wilmet\n- Player Downed - Arrisi\n- Player Downed - Gregers\n- Player Downed - Jo\n- Player Downed - Lorens\n- Player Downed - Vivian\n- Player Downed - Oski\n\n# Reviving Player\n- Reviving Player - Carden\n- Reviving Player - Kalisa\n- Reviving Player - Marian\n- Reviving Player - Sorrel\n- Reviving Player - Wilmet\n- Reviving Player - Arrisi\n- Reviving Player - Gregers\n- Reviving Player - Jo\n- Reviving Player - Lorens\n- Reviving Player - Vivian\n- Reviving Player - Oski\n\n# Character Downed Dialogues\n## Carden Downed\n- Kalisa: \"Carden! We'll get you up in a sec, buddy!\"\n- Marian: \"Frode has been incapacitated, sir.\"\n- Sorrel: \"Damn! Carden's down! Stay calm, mate!\"\n- Wilmet: \"Carden's been downed, sir.\"\n\n## Reviving Carden\n- Kalisa\n- Marian\n- Sorrel\n- Wilmet\n- Arrisi\n\n## Kalisa Downed\n- Carden: \"Squad member down! Hang in there, Kalisa!\"\n- Marian: \"Bast is down. Don't make me help her.\"\n- Sorrel: \"Kalisa's been hit! This is really bad.\"\n- Wilmet: \"Kalisa's been incapacitated. Peace at last.\"\n\n## Reviving Kalisa\n- Carden\n- Marian\n- Sorrel\n- Wilmet\n- Arrisi\n\n## Marian Downed\n- Carden: \"Marian! Don't worry, we'll be there soon!\"\n- Kalisa: \"Marian! I'm gonna get you back up!\"\n- Sorrel: \"Oh, no. Sir, they got Marian!\"\n- Wilmet: \"Marian, no! Damn droids! I'll kill all of you!\"\n\n## Reviving Marian\n- Carden\n- Kalisa\n- Sorrel\n- Wilmet\n- Arrisi\n\n## Sorrel Downed\n- Carden: \"Sorrel's down! We've gotta help him!\"\n- Kalisa: \"Hold on Sorrel, we're coming!\"\n\n## Reviving Sorrel\n- Carden\n- Kalisa\n- Marian\n- Wilmet\n- Arrisi\n\n## Wilmet Downed\n- Carden: \"Hey, they got Wilmet!\"\n- Kalisa: \"Wilmet's down. Good riddance.\"\n- Marian: \"Sir, Wilmet's been downed!\"\n- Sorrel: \"Edith's down. We should leave him there.\"\n\n## Reviving Wilmet\n- Carden\n- Kalisa\n- Marian\n- Sorrel\n- Arrisi\n\n## Arrisi Downed\n- Carden\n- Kalisa\n- Marian\n- Sorrel\n- Wilmet\n- Gregers\n- Jo\n- Lorens\n- Vivian\n- Oski\n\n## Reviving Arrisi\n- Carden\n- Kalisa\n- Marian\n- Sorrel\n- Wilmet\n- Gregers\n- Jo\n- Lorens\n- Vivian\n- Oski\n\n## Gregers Downed\n- Arrisi\n- Jo\n- Lorens\n- Vivian\n- Oski\n\n## Reviving Gregers\n- Arrisi\n- Jo\n- Lorens\n- Vivian\n- Oski\n\n## Jo Downed\n- Arrisi\n- Gregers\n- Lorens\n- Vivian\n- Oski\n\n## Reviving Jo\n- Arrisi\n- Gregers\n- Lorens\n- Vivian\n- Oski\n\n## Lorens Downed\n- Arrisi\n- Gregers\n- Jo\n- Vivian\n- Oski\n\n## Reviving Lorens\n- Arrisi\n- Gregers\n- Jo\n- Vivian\n- Oski\n\n## Vivian Downed\n- Arrisi: \"Vivian, no! Metal monsters!\"\n- Gregers: \"Vivian's down! Please, let me assist her!\"\n\n## Reviving Vivian\n- Arrisi\n- Gregers\n- Jo\n- Lorens\n- Oski\n\n## Oski Downed\n- Arrisi: \"No, Oski! We'll get you up, buddy!\"\n- Gregers: \"Oski's down! Let me help him!\"\n\n## Reviving Oski\n- Arrisi\n- Gregers\n- Jo\n- Lorens\n- Vivian\n\n# X Downed\n- Carden\n- Kalisa\n- Marian\n- Sorrel\n- Wilmet\n- Arrisi\n- Gregers\n- Jo\n- Lorens\n- Vivian\n- Oski\n\n## Reviving X\n- Carden\n- Kalisa\n- Marian\n- Sorrel\n- Wilmet\n- Arrisi\n- Gregers\n- Jo\n- Lorens\n- Vivian\n- Oski\n\n# Disable Mine\n- Disable Mine - Carden\n- Disable Mine - Kalisa\n- Disable Mine - Marian\n- Disable Mine - Sorrel\n- Disable Mine - Wilmet\n- Disable Mine - Arrisi\n- Disable Mine - Gregers\n- Disable Mine - Jo\n- Disable Mine - Lorens\n- Disable Mine - Vivian\n- Disable Mine - Oski\n\n# Cancel Mine Disable\n- Cancel Mine Disable - Carden\n- Cancel Mine Disable - Kalisa\n- Cancel Mine Disable - Marian\n- Cancel Mine Disable - Sorrel\n- Cancel Mine Disable - Wilmet\n- Cancel Mine Disable - Arrisi\n- Cancel Mine Disable - Gregers\n- Cancel Mine Disable - Jo\n- Cancel Mine Disable - Lorens\n- Cancel Mine Disable - Vivian\n- Cancel Mine Disable - Oski\n\n# Mine Disable Complete\n- Mine Disable Complete - Carden\n- Mine Disable Complete - Kalisa\n- Mine Disable Complete - Marian\n- Mine Disable Complete - Sorrel\n- Mine Disable Complete - Wilmet\n- Mine Disable Complete - Arrisi\n- Mine Disable Complete - Gregers\n- Mine Disable Complete - Jo\n- Mine Disable Complete - Lorens\n- Mine Disable Complete - Vivian\n- Mine Disable Complete - Oski\n\n# Rewire Mine\n- Rewire Mine - Carden\n- Rewire Mine - Kalisa\n- Rewire Mine - Marian\n- Rewire Mine - Sorrel\n- Rewire Mine - Wilmet\n- Rewire Mine - Arrisi\n- Rewire Mine - Gregers\n- Rewire Mine - Jo\n- Rewire Mine - Lorens\n- Rewire Mine - Vivian\n- Rewire Mine - Oski\n\n# Cancel Rewire Mine\n\n# Rewire Mine Complete\n\n# Setup Trap\n- Setup Trap - Carden\n- Setup Trap - Kalisa\n- Setup Trap - Marian\n- Setup Trap - Sorrel\n- Setup Trap - Wilmet\n- Setup Trap - Arrisi\n- Setup Trap - Gregers\n- Setup Trap - Jo\n- Setup Trap - Lorens\n- Setup Trap - Vivian\n- Setup Trap - Oski\n\n# Cancel Trap Setup\n- Cancel Trap Setup - Carden\n- Cancel Trap Setup - Kalisa\n- Cancel Trap Setup - Marian\n- Cancel Trap Setup - Sorrel\n- Cancel Trap Setup - Wilmet\n- Cancel Trap Setup - Arrisi\n- Cancel Trap Setup - Gregers\n- Cancel Trap Setup - Jo\n- Cancel Trap Setup - Lorens\n- Cancel Trap Setup - Vivian\n- Cancel Trap Setup - Oski\n\n# Player Single Target\n- Player Single Target - Ultra Gyre\n- Player Single Target - Dredge\n- Player Single Target - Scope\n- Player Single Target - Siphon\n- Player Single Target - Siren\n- Player Single Target - Vector\n- Player Single Target - Soldier\n\n# Player Single Target Dialogues\n- Carden: \"Break that Gyre, Sentinel!\"\n- Kalisa: \"Take down that Ultra Gyre!\"\n- Marian: \"Stop that Dredge, Sentinel!\"\n- Sorrel: \"Astre, crack that scope!\"\n- Wilmet: \"Astre, power down that Siphon!\"\n- Arrisi: \"Silence that Siren, Astre!\"\n- Gregers: \"Take strict aim on that Vector, Sentinel!\"\n- Jo: \"Astre, neutralize that ACP soldier!\"\n- Lorens: \"Target that Gyre, Astre!\"\n- Vivian: \"Dismantle that Ultra Gyre, Astre!\"\n- Oski: \"Astre, don't let that Dredge get close!\"\n- Scope: \"Scope, don't let it hit us, Sentinel!\"\n- Siphon: \"Disconnect that Siphon, Sentinel!\"\n- Siren: \"Permanently mute that Siren, Sentinel.\"\n- Vector: \"Astre, bring down that Vector!\"\n- Soldier: \"Incapacitate that ACP soldier, Sentinel!\"\n\n# Player Group Target - Gyre\n- Player Group Target - Ultra Gyre\n- Player Group Target - Dredge\n- Player Group Target - Scope\n- Player Group Target - Siphon\n- Player Group Target - Siren\n- Player Group Target - Vector\n- Player Group Target - Soldier\n\n# Player Group Target Dialogues\n- Carden: \"Target that Gyre, squad!\"\n- Kalisa: \"Focus your fire on that Ultra Gyre, squad!\"\n- Marian: \"Demolish that Dredge, squad!\"\n- Sorrel: \"Shatter that Scope, squad!\"\n- Wilmet: \"Shut down that Siphon, squad!\"\n- Arrisi: \"Astre squad, muzzle that Siren!\"\n- Gregers: \"Let's smash that Gyre, Sentinels!\"\n- Jo: \"Astre squad, prioritize that Ultra Gyre!\"\n- Lorens: \"Sentinels, wreck that Dredge!\"\n- Vivian: \"Astre squad, crush that Scope!\"\n- Oski: \"Sentinels, decouple that Siphon!\"\n- Gyre: \"Turn that Siren's scream into a whisper, squad.\"\n- Ultra Gyre: \"Make it spin, Astre Squad.\"\n- Dredge: \"Bring that Ultra Gyre to its knees, Sentinels.\"\n- Scope: \"Flatten that Dredge, squad.\"\n- Siphon: \n- Siren: \"Plunge that Vector into the ground, squad.\"\n\n\n## Metadata\n- **Source**: on-command-wiki-pages/On_Command_VO.txt\n- **Type**: wiki\n- **Tags**: wiki, on-command-wiki-pages, character-design, dialogue\n- **Imported**: 2025-05-05T16:25:37.228Z",
  "source": {
    "type": "notebook",
    "path": "on-command-wiki-pages/On_Command_VO.txt",
    "importedAt": "2025-05-05T16:25:37.228Z"
  },
  "created": "2025-05-05T16:25:37.228Z",
  "modified": "2025-05-05T16:25:37.228Z",
  "tags": [
    "wiki",
    "on-command-wiki-pages",
    "character-design",
    "dialogue"
  ]
}