{
  "title": "reminder-of-akago",
  "content": "# reminder-of-akago\n\nContent-Type: text/x-zim-wiki\nWiki-Format: zim 0.6\nCreation-Date: 2024-08-15T22:07:19-07:00\n\n--------------------\nStory Narration (Dialogue for Mail Bear & Potential Prey) \n--------------------\n\nChapter 1\nChapter Objective Summary\n\nLevel 1\n\nAkago: Dawn had settled beyond her room, radiating a brilliant apricot tinted light which gleamed softly through the crystalline glass window. Luminescent rays of light ascended the sheets of her \nLittle: Wait, what?! That’s way too wordy man, you’re putting us to sleep! Use less words to convey the image!\nAkago: But, I worked so hard on that script! \nLittle: Forget the script, I want to stay conscious!\nAkago: Fine, fine, fine. (Clears Throat) \nAkago: snug bed, the light slaps her in the face and she wakes abruptly from her slumber. Gently awaking Autumn from her slumber. She rises to the light’s approach, (She Stirs) indicating her fleeting power, the untroubled days of her \n\n(Autumn rises quickly, she has a comedic looking bed-head) (She yawns loudly, and rolls out from the bed, flopping out onto the floor. She lies still for a moment, groans, rises abruptly, stretches, and walks into a nearby door and slams it shut. Sounds are heard from inside, shower running, toilet flushing, teeth brushing, and rummaging around. The door opens and she walks out in her usual apparel. Autumn stretches once more and the player now has control)\n\n\n## Metadata\n- **Source**: All of it Anything Everything At Once/reminder-of-akago.txt\n- **Type**: document\n- **Tags**: document, All_of_it_Anything_Everything_At_Once, dialogue, story\n- **Imported**: 2025-05-05T16:25:37.184Z",
  "source": {
    "type": "notebook",
    "path": "All of it Anything Everything At Once/reminder-of-akago.txt",
    "importedAt": "2025-05-05T16:25:37.184Z"
  },
  "created": "2025-05-05T16:25:37.184Z",
  "modified": "2025-05-05T16:25:37.184Z",
  "tags": [
    "document",
    "All_of_it_Anything_Everything_At_Once",
    "dialogue",
    "story"
  ]
}