{
  "title": "rstu-suggestions",
  "content": "# rstu-suggestions\n\nContent-Type: text/x-zim-wiki\nWiki-Format: zim 0.6\nCreation-Date: 2024-07-23T23:12:53-07:00\n\n====== rstu-suggestions ======\n\n\n\n\nFirst - Tenant Union Overview: Rent & Rights\n\nThe current landscape of housing in the U.S, as well as globally, is increasingly challenging, particularly with the economic strains brought on by the pandemic. Many households are at risk of eviction, and the cost of rent continues to rise, making it increasingly difficult for many to keep a roof over their heads.\n\nA Tenants Union offers a platform for tenants to harness collective action and empower themselves in their negotiations with landlords and property owners. Much like a labor union, a Tenants Union can serve as a protective body that ensures the rights and privileges of tenants, advocates for rent control, and works towards the right to remain. This collective approach has the power to significantly change the dynamics between landlords and tenants, giving tenants a stronger voice and better negotiation opportunities.\n\nOne key concept is the Opportunity to Purchase, a tenant's right to buy their rented property. This could be exercised individually or collectively, through not-for-profit community land trusts, limited equity cooperatives, or shared equity cooperatives. For example, a union could potentially negotiate for the use of outstanding rent debt as leverage to buy a building, turning a crisis into an opportunity for tenants to gain ownership and control over their housing.\n\nAdditionally, the concept of Topa (Tenant Opportunity to Purchase Act) Rights can be integral to a Tenants Union. This allows tenants the first right to purchase the property they're living in before the landlord sells it to a third party, thus giving tenants a say in the sale process and helping avoid situations where they may have to start their advocacy from scratch if the property changes hands.\n\nDeed restrictions can be used to keep housing permanently affordable by limiting the resale price of a home, ensuring that it remains within the affordable housing bracket even when sold in the future. Coupled with rent stabilization policies, these measures can provide long-term solutions for affordable housing.\n\nThe union can also emphasize 'Housing with Dignity', advocating for decent living conditions and the avoidance of tactics that make living conditions unbearable for tenants in order to vacate rent-controlled units, a common practice among corporate landlords.\n\nThe idea of mutual aid is central to the functioning of a Tenants Union. By standing together, tenants can provide support and assistance to each other, creating a stronger front against exploitative practices.\n\nHowever, the union should also be ready to exercise self-determination and reject offers that don't adequately recognize or meet their needs. While negotiation is part of the process, maintaining a strong stance on the fundamental rights and demands of tenants is crucial.\n\nWhile these points provide a compelling case for the formation of a Tenants Union, it's important to note that the specific details and effectiveness of these measures can vary greatly depending on local laws, the specific circumstances of the tenants involved, and the willingness of property owners to negotiate. Nonetheless, a well-organized and determined Tenants Union can be a powerful force in advocating for tenant rights and affordable housing.\n\nWhile I've provided a general overview of these concepts, it would be beneficial to consult with a local attorney or housing rights organization to understand the specific legal implications and strategies for implementing these concepts in your area.\n\n\n\n\n\n\n\n\n\n\nStarting a Tenant Union\n\nResearch: Before you begin, familiarize yourself with tenant rights, laws, and regulations in your city, state, or country. Understanding these rights will be crucial in conversations with fellow tenants and in your negotiations with landlords.\n\nIdentify the Issues: Speak with the residents you meet and try to understand the problems they're facing. This will give you a baseline understanding of the issues and help you identify the demands of the union. You might find common problems such as high rents, poor maintenance, or unfair eviction practices.\n\nReach Out to Tenants: Start contacting other tenants in your building or neighborhood. You can knock on doors, send letters, or even host a small gathering to discuss the issues. When speaking to tenants, explain the benefits of collective action, such as a stronger voice in negotiations with landlords and more power to demand fair treatment and rights.\n\nBuild a List of Demands: Based on the issues identified, compile a list of demands. This could include things like rent control, better maintenance, a halt to unfair evictions, or even the right to purchase the property. Remember, these demands should reflect the collective needs and desires of the tenants.\n\nForm a Core Group: Identify a group of committed individuals who are ready to devote time and energy to the cause. This core group can serve as the initial leaders of the union and can help with organizing meetings, coordinating with tenants, and communicating with landlords.\n\nHold a Meeting: Once you have a core group and a list of demands, it's time to hold a larger meeting with all interested tenants. Discuss your demands, decide on a course of action, and officially form your union.\n\nLegal Consultation: It may be beneficial to consult with a lawyer or a local tenant rights organization. They can provide valuable advice and guidance on legal aspects of your actions.\n\nCommunicate with the Landlord: Once your union is formed and your demands are clear, it's time to approach the landlord. This could be in the form of a letter, a meeting, or a formal negotiation. Remember, the goal is not confrontation, but negotiation.\n\nRemember, organizing a tenants union is a process that requires patience, dedication, and resilience. You're likely to face challenges and setbacks along the way, but with determination and collective action, you can work towards creating a more equitable and just housing situation. Good luck!\n\n\n\n(USA Facts) There are 15,000,000 vacant homes/apartments in the United States\n(USA Facts) There are more than 650,000 homeless in the United States\n\n\n\n\n\n\n\n\n\n\n\n\n\n\n\nThird - Types of Organization\n\nNot-for-Profit Community Land Trust (CLT): A community land trust is a nonprofit corporation that develops and stewards affordable housing, community gardens, civic buildings, commercial spaces and other community assets on behalf of a community. CLTs balance the needs of individuals to access land and maintain security of tenure with a communityâ€™s need to maintain affordability, economic diversity and local access to essential services. In a typical CLT model, the trust acquires land and maintains ownership of it permanently. When a home is built on the land, the trust sells the building but retains the land.\n\nLimited Equity Cooperative (LEC): A limited equity housing cooperative is a residential development owned and managed by a democratically governed, nonprofit cooperative corporation, such as a tenants' union. This is a model designed to enable long-term, affordable access to housing. It works by placing restrictions on the profits that members can make from selling their shares, preserving affordability for future low- to moderate-income residents.\n\nShared Equity Cooperative: Shared equity models create lasting affordable housing by preserving the affordability of homes in the face of rising housing costs. In shared equity cooperatives, residents own their homes collectively and share in the equity gains, but the cooperative places limits on home resale prices to maintain long-term affordability. This structure allows residents to build some equity over time while also keeping the housing affordable for future residents.\n\nPublic Housing: Public housing is a form of housing tenure in which the property is usually owned by a government authority, either central or local. These government authorities may be called a housing authority or housing corporation and are often tasked with operating housing for low-income households at rents they can afford. Public housing can range from single houses to high density apartments, and in many countries, it's a major part of the real estate sector.\n\nEach of these organization types has its unique features, and the best choice would depend on the specific circumstances, legal environment, and objectives of the tenants' union. For example, if the objective is to gain collective ownership of the property, then forming a limited equity cooperative or shared equity cooperative might be the most suitable option. On the other hand, if the goal is to ensure long-term affordability and control over the land, a community land trust might be the best fit. It would be beneficial to consult with a legal advisor or a housing organization to discuss these options in detail and choose the most suitable model.\n\n\n\n\n\n\n\n\n\n\n\n\n\n\n\n\n\n\n\n\n\n\n\n\n\n\nTenant Questions\n\n\t* How long have you been here?\n\t* How much is your rent?\n\t* Can I ask how much you get paid?\n\t* How many hours do you work? \n\t* What days do you have off?\n\t* How reliable has maintenance been?\n\t* Are there changes you'd like to see?\n\t* What additions would be good to have?\n\t* How many people live here?\n\t* Do you have any pets?\n\t* What would the ideal rent be? (Or how much do you think is fair?)\n\t* Do you know any of your neighbors?\n\t* How can I contact you?\n\n\nKey Words\n\n\t* Opportunity to purchase\n\t* Right to remain\n\t* Rent control\n\t* Point of sale: avoid it\n\t* Topa rights\n\t* Not for profit community land trust\n\t* Shared equity cooperative\n\t* Public housing\n\t* Self-determination\n\t* Limited equity cooperative\n\t* Deed restrictions to make it permanently affordable\n\t* Rent stabilization\n\t* Housing with dignity\n\t* Mutual aid\n\n\n## Metadata\n- **Source**: All of it Anything Everything At Once/rstu-suggestions.txt\n- **Type**: document\n- **Tags**: document, All_of_it_Anything_Everything_At_Once, quest, feature\n- **Imported**: 2025-05-05T16:25:37.190Z",
  "source": {
    "type": "notebook",
    "path": "All of it Anything Everything At Once/rstu-suggestions.txt",
    "importedAt": "2025-05-05T16:25:37.190Z"
  },
  "created": "2025-05-05T16:25:37.190Z",
  "modified": "2025-05-05T16:25:37.190Z",
  "tags": [
    "document",
    "All_of_it_Anything_Everything_At_Once",
    "quest",
    "feature"
  ]
}